flask_autorouter/__init__.py
flask_autorouter-0.2.2.dist-info/LICENSE.txt
flask_autorouter-0.2.2.dist-info/METADATA
flask_autorouter-0.2.2.dist-info/WHEEL
flask_autorouter-0.2.2.dist-info/top_level.txt
flask_autorouter-0.2.2.dist-info/RECORD
